oozappa/__init__.py
oozappa/config.py
oozappa/fabrictools.py
oozappa/forms.py
oozappa/webui.py
oozappa/zappa.py
oozappa/_structure/_environment/vars.py
oozappa/_structure/_environment/fabfile/__init__.py
oozappa/_structure/_environment/templates/REMOVEME.txt
oozappa/_structure/common/__init__.py
oozappa/_structure/common/vars.py
oozappa/_structure/common/functions/REMOVEME.txt
oozappa/records/__init__.py
oozappa/static/css/gumby.css
oozappa/static/css/style.css
oozappa/templates/base.html
oozappa/templates/create_jobset.html
oozappa/templates/environment.html
oozappa/templates/environment_list.html
oozappa/templates/index.html
oozappa/templates/job.html
oozappa/templates/jobset.html
oozappa/templates/jobset_list.html
oozappa-0.9.1.dist-info/DESCRIPTION.rst
oozappa-0.9.1.dist-info/METADATA
oozappa-0.9.1.dist-info/RECORD
oozappa-0.9.1.dist-info/WHEEL
oozappa-0.9.1.dist-info/entry_points.txt
oozappa-0.9.1.dist-info/metadata.json
oozappa-0.9.1.dist-info/top_level.txt
