Metadata-Version: 2.0
Name: oozappa
Version: 0.9.1
Summary: Fabric task runner and helper. Executes and manages tasks via web browser.
Home-page: https://github.com/tsuyukimakoto/oozappa
Author: makoto tsuyuki
Author-email: mtsuyuki@gmail.com
License: UNKNOWN
Platform: UNKNOWN
Classifier: Development Status :: 3 - Alpha
Classifier: Environment :: Console
Classifier: Environment :: Web Environment
Classifier: Intended Audience :: Developers
Classifier: Intended Audience :: System Administrators
Classifier: License :: OSI Approved :: MIT License
Classifier: Operating System :: MacOS :: MacOS X
Classifier: Operating System :: POSIX
Classifier: Operating System :: Unix
Classifier: Programming Language :: Python
Classifier: Programming Language :: Python :: 2.7
Classifier: Topic :: Software Development
Classifier: Topic :: Software Development :: Build Tools
Classifier: Topic :: Software Development :: Libraries
Classifier: Topic :: Software Development :: Libraries :: Python Modules
Classifier: Topic :: System :: Clustering
Classifier: Topic :: System :: Software Distribution
Classifier: Topic :: System :: Systems Administration
Requires-Dist: Fabric (>=1.8.3)
Requires-Dist: Flask-WTF (>=0.9.5)
Requires-Dist: Flask-SQLAlchemy (>=1.0)
Requires-Dist: Flask-Sockets (>=0.1)
Requires-Dist: Jinja2 (>=2.7.2)
Requires-Dist: Pygments (>=1.6)
Requires-Dist: gevent-websocket (>=0.9.3)
Requires-Dist: gunicorn (>=18.0)
Requires-Dist: filelock (>=0.2.0)
